mystring/__init__.py
mystring-0.2.251.dist-info/LICENSE
mystring-0.2.251.dist-info/METADATA
mystring-0.2.251.dist-info/WHEEL
mystring-0.2.251.dist-info/top_level.txt
mystring-0.2.251.dist-info/RECORD
